deepcivics/__init__.py
deepcivics/autogen.py
deepcivics/civic_action.py
deepcivics/config.py
deepcivics/datasets.py
deepcivics/ingestion.py
deepcivics/llm.py
deepcivics/models.py
deepcivics/visualization.py
deepcivics-0.1.3.dist-info/licenses/LICENSE
deepcivics-0.1.3.dist-info/METADATA
deepcivics-0.1.3.dist-info/WHEEL
deepcivics-0.1.3.dist-info/top_level.txt
deepcivics-0.1.3.dist-info/RECORD
